divergence_resolver/__init__.py
divergence_resolver/main.py
divergence_resolver-1.0.1.dist-info/METADATA
divergence_resolver-1.0.1.dist-info/WHEEL
divergence_resolver-1.0.1.dist-info/top_level.txt
divergence_resolver-1.0.1.dist-info/RECORD
