Metadata-Version: 2.1
Name: divergence-resolver
Version: 1.0.1
Summary: A divergence_resolver.
Home-page: UNKNOWN
Author: zh_lgp
Author-email: 1158200486@qq.com
License: MIT
Keywords: divergence_resolver
Platform: UNKNOWN
